<?xml version="1.0"?>
<tree typeId="http://www.w3.org/1999/02/22-rdf-syntax-ns#type" baseUri="http://www.disit.org/km4city/resource/" isStateful="true">
	<instanceIterationQuery>
		<server>http://servicemap.disit.org/WebAppGrafo/sparql</server>
		<query>SELECT DISTINCT ?id WHERE {?s a km4c:SensorSite. ?s dcterms:identifier ?id.filter(!strstarts(?id,"METRO"))} limit 10</query>
	</instanceIterationQuery>
	<fileInfo>
		<fileName>sensorsite.n3</fileName>
		<startDirectory>./sensorsite</startDirectory>
	</fileInfo>
	<iterationElement>
		<attributes>
			<prop>
				<type>previusstate</type>	
				<name>testVar3</name>
				<defaultValue>78</defaultValue>
				<refValue>#[1]['FI055ZTL00801']{concentration}</refValue>	
			</prop>
			<prop>
				<type>valueExpression</type>
				<name>testVar2</name>
				<valueExpression>${testVar3} + 44</valueExpression>
			</prop>
		</attributes>
		<instance type="http://www.disit.org/km4city/schema#SensorSite" name="SensorSite" isRoot="true">
			<properties>
				<prop key="http://purl.org/dc/terms/identifier" isPrimaryKey="true">
					<type>id</type>
				</prop>
				<prop key="http://www.disit.org/km4city/schema#hasObservation">
					<type>Observation</type>
				</prop>
			</properties>
		</instance>
		<instance type="http://www.disit.org/km4city/schema#Observation" name="Observation" baseUri="http://www.disit.org/km4city/resource/obs/">
			<properties>
				<prop key="http://purl.org/dc/terms/identifier" isPrimaryKey="true">
					<type>UUID</type>
				</prop>
				<prop key="http://purl.org/dc/terms/date">
					<type>DateTime</type>
					<uri>http://www.w3.org/2001/XMLSchema#dateTime</uri>
				</prop>
				<prop key="http://www.disit.org/km4city/schema#lastAverageSpeed">
					<type>query</type>
					<queryInfo>
					<server>http://servicemap.disit.org/WebAppGrafo/sparql</server>
					<query>select ?speed where {
?s a km4c:SensorSite.
?s dcterms:identifier '${id}'.
?s km4c:hasObservation ?o.
?o km4c:averageSpeed ?speed.
?o dcterms:date ?d.
} order by desc(?d) limit 1</query>
					</queryInfo>
				</prop>
				<prop key="http://www.disit.org/km4city/schema#averageSpeed">
					<type>float</type>
					<maxValue>3</maxValue>
					<minValue>2</minValue>
					<name>averageSpeed</name>
					<uri>http://www.w3.org/2001/XMLSchema#float</uri>
				</prop>
				<prop key="http://www.disit.org/km4city/schema#vehicleFlow">
					<type>valueExpression</type>
					<valueExpression>${concentration} * ${averageSpeed} </valueExpression>
					<uri>http://www.w3.org/2001/XMLSchema#float</uri>
				</prop>
				<prop key="http://www.disit.org/km4city/schema#concentration">
					<type>float</type>
					<maxValue>3</maxValue>
					<minValue>2</minValue>
					<name>concentration</name>
					<uri>http://www.w3.org/2001/XMLSchema#float</uri>
				</prop>
				<prop key="http://www.disit.org/km4city/schema#measuredTime">
					<type>Instant</type>
				</prop>
				<prop key="http://www.disit.org/km4city/schema#measuredBySensor">
					<type>SensorSite</type>
				</prop>
			</properties>
		</instance>
		<instance type="http://www.w3.org/2006/time#Instant" name="Instant" >
			<properties>
				<prop key="http://purl.org/dc/terms/identifier" isPrimaryKey="true">
					<type>DateTime</type>
					<name>dateTime</name>
				</prop>
				<prop key="http://www.disit.org/km4city/schema#instantObserv">
					<type>Observation</type>
				</prop>
				<prop key="http://www.disit.org/km4city/schema#valueForegoing">
					<type>valueExpression</type>
					<valueExpression>${testVar2}+" cani "+${index}</valueExpression>
				</prop>
			</properties>
		</instance>
	</iterationElement>
</tree>
